{
  "name" : "Data Privacy Compliance in Food Systems",
  "name_en" : "Data Privacy Compliance in Food Systems",
  "id" : "0c34898c-e59f-459c-823f-f14d7507623e",
  "description" : "Data Privacy Compliance in Food Systems is the technical skill set required to ensure that personal and sensitive data collected, processed, and transmitted throughout digitalized food supply chains is handled in accordance with relevant data protection laws, industry standards, and best practices. As food systems become increasingly reliant on digital technologies—such as IoT sensors, blockchain traceability, cloud-based inventory management, and consumer-facing apps—vast amounts of data are generated, including supplier information, employee records, and consumer purchase histories. This skill involves understanding and applying regulations such as the General Data Protection Regulation (GDPR), the California Consumer Privacy Act (CCPA), and sector-specific guidelines to safeguard data at every stage of the food supply chain. Practitioners must be adept at conducting privacy impact assessments, implementing data minimization and anonymization techniques, managing consent, and ensuring secure data storage and transfer. They must also coordinate with IT, legal, and operational teams to develop and enforce privacy policies, respond to data breaches, and maintain audit trails for compliance verification. Immediate applications include protecting consumer trust, avoiding regulatory penalties, and enabling secure data sharing between supply chain partners. This skill is critical today as food companies face heightened scrutiny from regulators and consumers alike, making robust data privacy compliance a non-negotiable aspect of technical operations in the food sector.\n\nDomain: General\nDomain Description: General skills that don't fit cleanly into other categories\nSkill Type: NotSet\nSkill Areas: Technical, Process\nRelevance Score: 1.2\nGenerated by: Frøya v2.0.0\nOperation ID: FR-20250422-d9069681",
  "description_en" : "Data Privacy Compliance in Food Systems is the technical skill set required to ensure that personal and sensitive data collected, processed, and transmitted throughout digitalized food supply chains is handled in accordance with relevant data protection laws, industry standards, and best practices. As food systems become increasingly reliant on digital technologies—such as IoT sensors, blockchain traceability, cloud-based inventory management, and consumer-facing apps—vast amounts of data are generated, including supplier information, employee records, and consumer purchase histories. This skill involves understanding and applying regulations such as the General Data Protection Regulation (GDPR), the California Consumer Privacy Act (CCPA), and sector-specific guidelines to safeguard data at every stage of the food supply chain. Practitioners must be adept at conducting privacy impact assessments, implementing data minimization and anonymization techniques, managing consent, and ensuring secure data storage and transfer. They must also coordinate with IT, legal, and operational teams to develop and enforce privacy policies, respond to data breaches, and maintain audit trails for compliance verification. Immediate applications include protecting consumer trust, avoiding regulatory penalties, and enabling secure data sharing between supply chain partners. This skill is critical today as food companies face heightened scrutiny from regulators and consumers alike, making robust data privacy compliance a non-negotiable aspect of technical operations in the food sector.",
  "coversElement" : {
    "classification" : "NotSet"
  },
  "taggedWith" : [ ],
  "skillDomains" : [ ],
  "skillAreaCategories" : [ ],
  "matchesArea" : [ {
    "skillAreaClassification" : "Technical"
  }, {
    "skillAreaClassification" : "NotSet"
  }, {
    "skillAreaClassification" : "Process"
  } ],
  "skillType" : {
    "skillTypeClassification" : "NotSet"
  },
  "relatesTo" : [ ],
  "isCompositeOf" : [ ],
  "isExtensionOf" : [ ],
  "additionaljsonproperties" : null,
  "skillOwner" : "668d08a9-810e-440c-a668-531a1624694d",
  "skillOwnerUsername" : "Frøya co-worker",
  "editedBy" : "668d08a9-810e-440c-a668-531a1624694d",
  "editedByUsername" : "Frøya co-worker",
  "networkReference" : null,
  "currentVersion" : 1,
  "createdAt" : [ 2025, 4, 22, 15, 37, 21, 508158000 ],
  "lastEdited" : [ 2025, 4, 22, 15, 37, 21, 508153000 ],
  "hide" : false,
  "public" : true,
  "relatesToSkill" : [ ],
  "isCompositeOfSkill" : [ ],
  "isExtensionOfSkill" : [ ]
}