{
  "name" : "Enterprise Sales Objection Handling",
  "name_en" : "Enterprise Sales Objection Handling",
  "id" : "e4a657dc-ee25-4e1b-b4c0-c1a8853aa954",
  "description" : "Enterprise Sales Objection Handling is the specialized skill of effectively identifying, addressing, and overcoming objections that arise during the sales process for large, complex deals involving multiple stakeholders, extended sales cycles, and high-value contracts. In today's business environment, enterprise sales are characterized by intricate decision-making structures, rigorous procurement processes, and heightened scrutiny from various departments such as IT, legal, finance, and executive leadership. This skill requires a deep understanding of both the client's business drivers and the internal dynamics of large organizations. Practitioners must be adept at uncovering the root causes behind stated objections, which often include concerns about risk, ROI, integration, compliance, and change management. Successful objection handling in this context involves not only responding to explicit concerns but also proactively anticipating hidden or unspoken reservations that may be held by different stakeholders. Techniques such as consultative questioning, value-based selling, stakeholder mapping, and tailored communication are essential. The skill is immediately relevant as organizations increasingly prioritize risk mitigation and cost justification, making objection handling a critical differentiator for sales professionals. Mastery of this skill leads to higher win rates, shorter sales cycles, and stronger client relationships, as it demonstrates credibility, builds trust, and aligns solutions with the enterprise's strategic objectives.\n\nDomain: Marketing & Sales\nDomain Description: Marketing, sales, customer acquisition, and retention\nSkill Type: Transferable and Functional\nSkill Areas: Experience, Process\nRelevance Score: 1.2\nGenerated by: Frøya v2.0.0\nOperation ID: FR-20250422-39e8e92e",
  "description_en" : "Enterprise Sales Objection Handling is the specialized skill of effectively identifying, addressing, and overcoming objections that arise during the sales process for large, complex deals involving multiple stakeholders, extended sales cycles, and high-value contracts. In today's business environment, enterprise sales are characterized by intricate decision-making structures, rigorous procurement processes, and heightened scrutiny from various departments such as IT, legal, finance, and executive leadership. This skill requires a deep understanding of both the client's business drivers and the internal dynamics of large organizations. Practitioners must be adept at uncovering the root causes behind stated objections, which often include concerns about risk, ROI, integration, compliance, and change management. Successful objection handling in this context involves not only responding to explicit concerns but also proactively anticipating hidden or unspoken reservations that may be held by different stakeholders. Techniques such as consultative questioning, value-based selling, stakeholder mapping, and tailored communication are essential. The skill is immediately relevant as organizations increasingly prioritize risk mitigation and cost justification, making objection handling a critical differentiator for sales professionals. Mastery of this skill leads to higher win rates, shorter sales cycles, and stronger client relationships, as it demonstrates credibility, builds trust, and aligns solutions with the enterprise's strategic objectives.",
  "coversElement" : {
    "classification" : "Management_Leadership"
  },
  "taggedWith" : [ ],
  "skillDomains" : [ ],
  "skillAreaCategories" : [ ],
  "matchesArea" : [ {
    "skillAreaClassification" : "Process"
  }, {
    "skillAreaClassification" : "Experience"
  } ],
  "skillType" : {
    "skillTypeClassification" : "Transferable_and_Functional"
  },
  "relatesTo" : [ ],
  "isCompositeOf" : [ ],
  "isExtensionOf" : [ ],
  "additionaljsonproperties" : null,
  "skillOwner" : "668d08a9-810e-440c-a668-531a1624694d",
  "skillOwnerUsername" : "Frøya co-worker",
  "editedBy" : "668d08a9-810e-440c-a668-531a1624694d",
  "editedByUsername" : "Frøya co-worker",
  "networkReference" : null,
  "currentVersion" : 1,
  "createdAt" : [ 2025, 4, 22, 19, 36, 38, 941109000 ],
  "lastEdited" : [ 2025, 4, 22, 19, 36, 38, 941107000 ],
  "hide" : false,
  "public" : true,
  "relatesToSkill" : [ ],
  "isCompositeOfSkill" : [ ],
  "isExtensionOfSkill" : [ ]
}