{
  "name" : "human resources",
  "name_en" : null,
  "id" : "97cddc0b-12a5-4c21-be06-27e1965ed372",
  "description" : "Human resources is used to describe both the people who work for a company or organization and the department responsible for managing all matters related to employees, who collectively represent one of the most valuable resources in any businesses or organization. ",
  "description_en" : "human resources",
  "coversElement" : {
    "classification" : "NotSet"
  },
  "taggedWith" : [ ],
  "matchesArea" : [ ],
  "skillType" : {
    "skillTypeClassification" : "NotSet"
  },
  "relatesTo" : [ ],
  "isCompositeOf" : [ ],
  "isExtensionOf" : [ ],
  "additionaljsonproperties" : null,
  "skillOwner" : "61d38553-5d09-4cd3-a06a-c7173e6c1947",
  "skillOwnerUsername" : "Thor Henning Hetland",
  "editedBy" : "61d38553-5d09-4cd3-a06a-c7173e6c1947",
  "editedByUsername" : "Thor Henning Hetland",
  "networkReference" : null,
  "currentVersion" : 0,
  "createdAt" : [ 2022, 8, 17, 12, 22, 11, 387982000 ],
  "lastEdited" : [ 2022, 8, 17, 12, 22, 11, 387977000 ],
  "public" : true,
  "relatesToSkill" : [ ],
  "isCompositeOfSkill" : [ ],
  "isExtensionOfSkill" : [ ]
}