{
  "name" : "NoOps",
  "name_en" : null,
  "id" : "a92ef4e3-e522-48a5-8f43-a2a5a99bb12d",
  "description" : "NoOps (or No Operations) is an approach to software development that seeks to reduce the amount of manual operations required to maintain a software system. It focuses on automating the entire software lifecycle, from development to deployment and maintenance. NoOps is often used in custom software development to reduce the amount of time and effort required to maintain a system.\n",
  "description_en" : "noops",
  "coversElement" : {
    "classification" : "Technical"
  },
  "taggedWith" : [ ],
  "matchesArea" : [ {
    "skillAreaClassification" : "Technical"
  } ],
  "skillType" : {
    "skillTypeClassification" : "Transferable_and_Functional"
  },
  "relatesTo" : [ {
    "id" : "8fea120a-4660-4be7-9faa-5254d71cfe9f",
    "name" : "java-auto update (jau)",
    "description" : null,
    "description_en" : null
  }, {
    "id" : "f6c41941-1ed2-46b1-ad6f-40d3c9a4af22",
    "name" : "configservice",
    "description" : null,
    "description_en" : null
  }, {
    "id" : "456e7fff-c1c9-4e71-8b29-c4f832b864e8",
    "name" : "Configuration Management (CM)",
    "description" : null,
    "description_en" : null
  } ],
  "isCompositeOf" : [ ],
  "isExtensionOf" : [ {
    "id" : "3c854aa5-ad7f-4cd7-8e82-22b23ed102ac",
    "name" : "Continuous deployment",
    "description" : null,
    "description_en" : null
  }, {
    "id" : "23b0c47a-d3d8-4eaf-8ccc-1ecf0fe1aff4",
    "name" : "Continuous Delivery",
    "description" : null,
    "description_en" : null
  } ],
  "additionaljsonproperties" : null,
  "skillOwner" : "61d38553-5d09-4cd3-a06a-c7173e6c1947",
  "skillOwnerUsername" : "Thor Henning Hetland",
  "editedBy" : "61d38553-5d09-4cd3-a06a-c7173e6c1947",
  "editedByUsername" : "Thor Henning Hetland",
  "networkReference" : null,
  "currentVersion" : 1,
  "createdAt" : [ 2022, 5, 23, 10, 55, 15, 863007000 ],
  "lastEdited" : [ 2022, 12, 13, 11, 30, 17, 212879000 ],
  "public" : true,
  "isExtensionOfSkill" : [ {
    "name" : "Continuous deployment",
    "name_en" : null,
    "id" : "dd0d6bd3-d4c9-479d-a009-49c7159bf282",
    "description" : "Continuous deployment",
    "description_en" : "Continuous deployment",
    "coversElement" : {
      "classification" : "NotSet"
    },
    "taggedWith" : [ ],
    "matchesArea" : [ ],
    "skillType" : {
      "skillTypeClassification" : "NotSet"
    },
    "relatesTo" : [ ],
    "isCompositeOf" : [ ],
    "isExtensionOf" : [ ],
    "additionaljsonproperties" : null,
    "skillOwner" : null,
    "skillOwnerUsername" : null,
    "editedBy" : null,
    "editedByUsername" : null,
    "networkReference" : null,
    "currentVersion" : 0,
    "createdAt" : null,
    "lastEdited" : null,
    "public" : false,
    "isExtensionOfSkill" : [ ],
    "isCompositeOfSkill" : [ ],
    "relatesToSkill" : [ ]
  }, {
    "name" : "Continuous deployment",
    "name_en" : null,
    "id" : "dd0d6bd3-d4c9-479d-a009-49c7159bf282",
    "description" : "Continuous deployment",
    "description_en" : "Continuous deployment",
    "coversElement" : {
      "classification" : "NotSet"
    },
    "taggedWith" : [ ],
    "matchesArea" : [ ],
    "skillType" : {
      "skillTypeClassification" : "NotSet"
    },
    "relatesTo" : [ ],
    "isCompositeOf" : [ ],
    "isExtensionOf" : [ ],
    "additionaljsonproperties" : null,
    "skillOwner" : null,
    "skillOwnerUsername" : null,
    "editedBy" : null,
    "editedByUsername" : null,
    "networkReference" : null,
    "currentVersion" : 0,
    "createdAt" : null,
    "lastEdited" : null,
    "public" : false,
    "isExtensionOfSkill" : [ ],
    "isCompositeOfSkill" : [ ],
    "relatesToSkill" : [ ]
  }, {
    "name" : "Continuous Delivery",
    "name_en" : null,
    "id" : "e34f831a-f676-456c-87bc-c59e5d5fd654",
    "description" : "Continuous Delivery",
    "description_en" : "Continuous Delivery",
    "coversElement" : {
      "classification" : "NotSet"
    },
    "taggedWith" : [ ],
    "matchesArea" : [ ],
    "skillType" : {
      "skillTypeClassification" : "NotSet"
    },
    "relatesTo" : [ ],
    "isCompositeOf" : [ ],
    "isExtensionOf" : [ ],
    "additionaljsonproperties" : null,
    "skillOwner" : null,
    "skillOwnerUsername" : null,
    "editedBy" : null,
    "editedByUsername" : null,
    "networkReference" : null,
    "currentVersion" : 0,
    "createdAt" : null,
    "lastEdited" : null,
    "public" : false,
    "isExtensionOfSkill" : [ ],
    "isCompositeOfSkill" : [ ],
    "relatesToSkill" : [ ]
  }, {
    "name" : "Continuous Delivery",
    "name_en" : null,
    "id" : "e34f831a-f676-456c-87bc-c59e5d5fd654",
    "description" : "Continuous Delivery",
    "description_en" : "Continuous Delivery",
    "coversElement" : {
      "classification" : "NotSet"
    },
    "taggedWith" : [ ],
    "matchesArea" : [ ],
    "skillType" : {
      "skillTypeClassification" : "NotSet"
    },
    "relatesTo" : [ ],
    "isCompositeOf" : [ ],
    "isExtensionOf" : [ ],
    "additionaljsonproperties" : null,
    "skillOwner" : null,
    "skillOwnerUsername" : null,
    "editedBy" : null,
    "editedByUsername" : null,
    "networkReference" : null,
    "currentVersion" : 0,
    "createdAt" : null,
    "lastEdited" : null,
    "public" : false,
    "isExtensionOfSkill" : [ ],
    "isCompositeOfSkill" : [ ],
    "relatesToSkill" : [ ]
  } ],
  "isCompositeOfSkill" : [ ],
  "relatesToSkill" : [ {
    "name" : "java-auto update (jau)",
    "name_en" : null,
    "id" : "981a48f1-dedc-48d0-b5e0-94483ca3ec17",
    "description" : "java-auto update (jau)",
    "description_en" : "java-auto update (jau)",
    "coversElement" : {
      "classification" : "NotSet"
    },
    "taggedWith" : [ ],
    "matchesArea" : [ ],
    "skillType" : {
      "skillTypeClassification" : "NotSet"
    },
    "relatesTo" : [ ],
    "isCompositeOf" : [ ],
    "isExtensionOf" : [ ],
    "additionaljsonproperties" : null,
    "skillOwner" : null,
    "skillOwnerUsername" : null,
    "editedBy" : null,
    "editedByUsername" : null,
    "networkReference" : null,
    "currentVersion" : 0,
    "createdAt" : null,
    "lastEdited" : null,
    "public" : false,
    "isExtensionOfSkill" : [ ],
    "isCompositeOfSkill" : [ ],
    "relatesToSkill" : [ ]
  }, {
    "name" : "configservice",
    "name_en" : null,
    "id" : "33a7522c-3e77-402a-8574-3b82aca73b28",
    "description" : "configservice",
    "description_en" : "configservice",
    "coversElement" : {
      "classification" : "NotSet"
    },
    "taggedWith" : [ ],
    "matchesArea" : [ ],
    "skillType" : {
      "skillTypeClassification" : "NotSet"
    },
    "relatesTo" : [ ],
    "isCompositeOf" : [ ],
    "isExtensionOf" : [ ],
    "additionaljsonproperties" : null,
    "skillOwner" : null,
    "skillOwnerUsername" : null,
    "editedBy" : null,
    "editedByUsername" : null,
    "networkReference" : null,
    "currentVersion" : 0,
    "createdAt" : null,
    "lastEdited" : null,
    "public" : false,
    "isExtensionOfSkill" : [ ],
    "isCompositeOfSkill" : [ ],
    "relatesToSkill" : [ ]
  }, {
    "name" : "Configuration Management (CM)",
    "name_en" : null,
    "id" : "26b24a3b-9822-42f9-a9bb-8d6de151ca91",
    "description" : "Configuration Management (CM)",
    "description_en" : "Configuration Management (CM)",
    "coversElement" : {
      "classification" : "NotSet"
    },
    "taggedWith" : [ ],
    "matchesArea" : [ ],
    "skillType" : {
      "skillTypeClassification" : "NotSet"
    },
    "relatesTo" : [ ],
    "isCompositeOf" : [ ],
    "isExtensionOf" : [ ],
    "additionaljsonproperties" : null,
    "skillOwner" : null,
    "skillOwnerUsername" : null,
    "editedBy" : null,
    "editedByUsername" : null,
    "networkReference" : null,
    "currentVersion" : 0,
    "createdAt" : null,
    "lastEdited" : null,
    "public" : false,
    "isExtensionOfSkill" : [ ],
    "isCompositeOfSkill" : [ ],
    "relatesToSkill" : [ ]
  } ]
}