{
  "name" : "problem-solving",
  "name_en" : null,
  "id" : "8394000f-602a-4390-a106-d334d9be792b",
  "description" : " ",
  "description_en" : "problem-solving",
  "coversElement" : {
    "classification" : "NotSet"
  },
  "taggedWith" : [ ],
  "matchesArea" : [ ],
  "skillType" : {
    "skillTypeClassification" : "NotSet"
  },
  "relatesTo" : [ ],
  "isCompositeOf" : [ ],
  "isExtensionOf" : [ ],
  "additionaljsonproperties" : null,
  "skillOwner" : "3e924f56-aee0-42f9-aecb-3c14ebbfba81",
  "skillOwnerUsername" : "Selina Quadim",
  "editedBy" : "3e924f56-aee0-42f9-aecb-3c14ebbfba81",
  "editedByUsername" : "Selina Quadim",
  "networkReference" : null,
  "currentVersion" : 0,
  "createdAt" : [ 2023, 1, 25, 20, 30, 33, 302464000 ],
  "lastEdited" : [ 2023, 1, 25, 20, 30, 33, 302458000 ],
  "public" : true,
  "relatesToSkill" : [ ],
  "isExtensionOfSkill" : [ ],
  "isCompositeOfSkill" : [ ]
}