{
  "name" : "Public Skill 179",
  "name_en" : null,
  "id" : "823cd2df-d878-4e2f-a552-801babc6067d",
  "description" : "Public Skill 179",
  "description_en" : "Public Skill 179",
  "coversElement" : {
    "classification" : "NotSet"
  },
  "taggedWith" : [ ],
  "matchesArea" : [ ],
  "skillType" : {
    "skillTypeClassification" : "NotSet"
  },
  "relatesTo" : [ ],
  "isCompositeOf" : [ ],
  "isExtensionOf" : [ ],
  "additionaljsonproperties" : null,
  "skillOwner" : "Thor Henning Hetland",
  "skillOwnerUsername" : null,
  "editedBy" : null,
  "editedByUsername" : "Jose Diaz",
  "networkReference" : null,
  "currentVersion" : 0,
  "createdAt" : [ 2023, 10, 16, 23, 31, 2, 156373000 ],
  "lastEdited" : [ 2023, 10, 16, 23, 32, 12, 812046000 ],
  "public" : true,
  "relatesToSkill" : [ ],
  "isCompositeOfSkill" : [ ],
  "isExtensionOfSkill" : [ ]
}