{
  "name" : "Public Skill 179",
  "name_en" : null,
  "id" : "4061713a-edd0-47c1-b0a0-d3d004b0b11b",
  "description" : "Public Skill 179",
  "description_en" : "Public Skill 179",
  "coversElement" : {
    "classification" : "NotSet"
  },
  "taggedWith" : [ ],
  "matchesArea" : [ ],
  "skillType" : {
    "skillTypeClassification" : "NotSet"
  },
  "relatesTo" : [ ],
  "isCompositeOf" : [ ],
  "isExtensionOf" : [ ],
  "additionaljsonproperties" : null,
  "skillOwner" : "Thor Henning Hetland",
  "skillOwnerUsername" : null,
  "editedBy" : null,
  "editedByUsername" : "Jose Diaz",
  "networkReference" : null,
  "currentVersion" : 0,
  "createdAt" : [ 2023, 10, 17, 0, 21, 40, 137195000 ],
  "lastEdited" : [ 2023, 10, 17, 0, 22, 51, 186984000 ],
  "public" : true,
  "relatesToSkill" : [ ],
  "isCompositeOfSkill" : [ ],
  "isExtensionOfSkill" : [ ]
}