{
  "name" : "Public Skill 91",
  "name_en" : null,
  "id" : "03673f3b-7a1d-485d-a43b-df590f10f6ab",
  "description" : "Public Skill 91",
  "description_en" : "Public Skill 91",
  "coversElement" : {
    "classification" : "NotSet"
  },
  "taggedWith" : [ ],
  "matchesArea" : [ ],
  "skillType" : {
    "skillTypeClassification" : "NotSet"
  },
  "relatesTo" : [ ],
  "isCompositeOf" : [ ],
  "isExtensionOf" : [ ],
  "additionaljsonproperties" : null,
  "skillOwner" : "Thor Henning Hetland",
  "skillOwnerUsername" : null,
  "editedBy" : null,
  "editedByUsername" : "Jose Diaz",
  "networkReference" : null,
  "currentVersion" : 0,
  "createdAt" : [ 2023, 10, 16, 20, 26, 0, 190652000 ],
  "lastEdited" : [ 2023, 10, 16, 20, 26, 1, 217386000 ],
  "public" : true,
  "relatesToSkill" : [ ],
  "isCompositeOfSkill" : [ ],
  "isExtensionOfSkill" : [ ]
}