{
  "name" : "Public Skill 231",
  "name_en" : null,
  "id" : "cd5acea2-2533-4a74-8fda-6f2d30fbf871",
  "description" : "Public Skill 231",
  "description_en" : "Public Skill 231",
  "coversElement" : {
    "classification" : "NotSet"
  },
  "taggedWith" : [ ],
  "matchesArea" : [ ],
  "skillType" : {
    "skillTypeClassification" : "NotSet"
  },
  "relatesTo" : [ ],
  "isCompositeOf" : [ ],
  "isExtensionOf" : [ ],
  "additionaljsonproperties" : null,
  "skillOwner" : "Thor Henning Hetland",
  "skillOwnerUsername" : null,
  "editedBy" : null,
  "editedByUsername" : "Jose Diaz",
  "networkReference" : null,
  "currentVersion" : 0,
  "createdAt" : [ 2023, 10, 16, 23, 31, 2, 227794000 ],
  "lastEdited" : [ 2023, 10, 16, 23, 32, 33, 4853000 ],
  "public" : true,
  "relatesToSkill" : [ ],
  "isCompositeOfSkill" : [ ],
  "isExtensionOfSkill" : [ ]
}