{
  "name" : "Public Skill 287",
  "name_en" : null,
  "id" : "8c36237d-86a8-4d20-b504-485dc4dca339",
  "description" : "Public Skill 287",
  "description_en" : "Public Skill 287",
  "coversElement" : {
    "classification" : "NotSet"
  },
  "taggedWith" : [ ],
  "matchesArea" : [ ],
  "skillType" : {
    "skillTypeClassification" : "NotSet"
  },
  "relatesTo" : [ ],
  "isCompositeOf" : [ ],
  "isExtensionOf" : [ ],
  "additionaljsonproperties" : null,
  "skillOwner" : "Thor Henning Hetland",
  "skillOwnerUsername" : null,
  "editedBy" : null,
  "editedByUsername" : "Jose Diaz",
  "networkReference" : null,
  "currentVersion" : 0,
  "createdAt" : [ 2023, 10, 16, 19, 59, 53, 601572000 ],
  "lastEdited" : [ 2023, 10, 16, 19, 59, 56, 536648000 ],
  "public" : true,
  "relatesToSkill" : [ ],
  "isCompositeOfSkill" : [ ],
  "isExtensionOfSkill" : [ ]
}