{
  "name" : "Public Skill 436",
  "name_en" : null,
  "id" : "0c543581-dd78-4eed-94b6-5a2a078365c3",
  "description" : "Public Skill 436",
  "description_en" : "Public Skill 436",
  "coversElement" : {
    "classification" : "NotSet"
  },
  "taggedWith" : [ ],
  "matchesArea" : [ ],
  "skillType" : {
    "skillTypeClassification" : "NotSet"
  },
  "relatesTo" : [ ],
  "isCompositeOf" : [ ],
  "isExtensionOf" : [ ],
  "additionaljsonproperties" : null,
  "skillOwner" : "Thor Henning Hetland",
  "skillOwnerUsername" : null,
  "editedBy" : null,
  "editedByUsername" : "Jose Diaz",
  "networkReference" : null,
  "currentVersion" : 0,
  "createdAt" : [ 2023, 10, 17, 0, 21, 40, 428386000 ],
  "lastEdited" : [ 2023, 10, 17, 0, 24, 27, 601284000 ],
  "public" : true,
  "relatesToSkill" : [ ],
  "isCompositeOfSkill" : [ ],
  "isExtensionOfSkill" : [ ]
}