{
  "name" : "Public Skill 365",
  "name_en" : null,
  "id" : "51552909-fc50-4200-9f84-7dd09b863cf1",
  "description" : "Public Skill 365",
  "description_en" : "Public Skill 365",
  "coversElement" : {
    "classification" : "NotSet"
  },
  "taggedWith" : [ ],
  "matchesArea" : [ ],
  "skillType" : {
    "skillTypeClassification" : "NotSet"
  },
  "relatesTo" : [ ],
  "isCompositeOf" : [ ],
  "isExtensionOf" : [ ],
  "additionaljsonproperties" : null,
  "skillOwner" : "Thor Henning Hetland",
  "skillOwnerUsername" : null,
  "editedBy" : null,
  "editedByUsername" : "Jose Diaz",
  "networkReference" : null,
  "currentVersion" : 0,
  "createdAt" : [ 2023, 10, 16, 20, 7, 54, 508582000 ],
  "lastEdited" : [ 2023, 10, 16, 20, 7, 56, 938637000 ],
  "public" : true,
  "relatesToSkill" : [ ],
  "isCompositeOfSkill" : [ ],
  "isExtensionOfSkill" : [ ]
}