{
  "name" : "Public Skill 4",
  "name_en" : null,
  "id" : "7ded727d-49f5-459b-9b6d-42dfb30ab81a",
  "description" : "Public Skill 4",
  "description_en" : "Public Skill 4",
  "coversElement" : {
    "classification" : "NotSet"
  },
  "taggedWith" : [ ],
  "matchesArea" : [ ],
  "skillType" : {
    "skillTypeClassification" : "NotSet"
  },
  "relatesTo" : [ ],
  "isCompositeOf" : [ ],
  "isExtensionOf" : [ ],
  "additionaljsonproperties" : null,
  "skillOwner" : "Thor Henning Hetland",
  "skillOwnerUsername" : null,
  "editedBy" : null,
  "editedByUsername" : "Jose Diaz",
  "networkReference" : null,
  "currentVersion" : 0,
  "createdAt" : [ 2023, 10, 18, 17, 16, 1, 791323000 ],
  "lastEdited" : [ 2023, 10, 18, 17, 16, 13, 106400000 ],
  "public" : true,
  "relatesToSkill" : [ ],
  "isCompositeOfSkill" : [ ],
  "isExtensionOfSkill" : [ ]
}