{
  "name" : "Sales Funnel Optimization",
  "name_en" : "Sales Funnel Optimization",
  "id" : "e2877171-0ce9-438c-8f43-70a054c9dddc",
  "description" : "Sales Funnel Optimization is the strategic process of analyzing, refining, and enhancing each stage of the sales funnel to maximize conversion rates and revenue generation. In today's highly competitive business environment, this skill is crucial for organizations seeking to streamline their sales processes, reduce customer acquisition costs, and improve overall profitability. Sales Funnel Optimization involves a data-driven approach to identifying bottlenecks, drop-off points, and inefficiencies within the funnel, from initial lead generation through to final purchase and post-sale engagement. Practitioners leverage tools such as CRM systems, analytics platforms, and A/B testing to monitor user behavior, segment audiences, and tailor messaging or offers to specific customer personas. Key activities include mapping the customer journey, optimizing landing pages, refining lead nurturing workflows, and implementing retargeting strategies. The skill also requires close collaboration with marketing, sales, and customer success teams to ensure alignment and consistency across touchpoints. Effective Sales Funnel Optimization leads to increased lead quality, higher conversion rates, shorter sales cycles, and improved customer lifetime value. It is immediately relevant for businesses of all sizes, especially those operating in digital or omnichannel environments, as it directly impacts revenue growth and competitive advantage in the current marketplace.\n\nDomain: Business Strategy\nDomain Description: Strategic planning, market analysis, and business development\nSkill Type: Knowledge Based\nSkill Areas: Organizational, Technical, Process\nRelevance Score: 1.2\nGenerated by: Frøya v2.0.0\nOperation ID: FR-20250422-39e8e92e",
  "description_en" : "Sales Funnel Optimization is the strategic process of analyzing, refining, and enhancing each stage of the sales funnel to maximize conversion rates and revenue generation. In today's highly competitive business environment, this skill is crucial for organizations seeking to streamline their sales processes, reduce customer acquisition costs, and improve overall profitability. Sales Funnel Optimization involves a data-driven approach to identifying bottlenecks, drop-off points, and inefficiencies within the funnel, from initial lead generation through to final purchase and post-sale engagement. Practitioners leverage tools such as CRM systems, analytics platforms, and A/B testing to monitor user behavior, segment audiences, and tailor messaging or offers to specific customer personas. Key activities include mapping the customer journey, optimizing landing pages, refining lead nurturing workflows, and implementing retargeting strategies. The skill also requires close collaboration with marketing, sales, and customer success teams to ensure alignment and consistency across touchpoints. Effective Sales Funnel Optimization leads to increased lead quality, higher conversion rates, shorter sales cycles, and improved customer lifetime value. It is immediately relevant for businesses of all sizes, especially those operating in digital or omnichannel environments, as it directly impacts revenue growth and competitive advantage in the current marketplace.",
  "coversElement" : {
    "classification" : "Management_Leadership"
  },
  "taggedWith" : [ ],
  "skillDomains" : [ ],
  "skillAreaCategories" : [ ],
  "matchesArea" : [ {
    "skillAreaClassification" : "Organizational"
  }, {
    "skillAreaClassification" : "Technical"
  }, {
    "skillAreaClassification" : "Process"
  } ],
  "skillType" : {
    "skillTypeClassification" : "Knowledge_Based"
  },
  "relatesTo" : [ ],
  "isCompositeOf" : [ ],
  "isExtensionOf" : [ ],
  "additionaljsonproperties" : null,
  "skillOwner" : "668d08a9-810e-440c-a668-531a1624694d",
  "skillOwnerUsername" : "Frøya co-worker",
  "editedBy" : "668d08a9-810e-440c-a668-531a1624694d",
  "editedByUsername" : "Frøya co-worker",
  "networkReference" : null,
  "currentVersion" : 1,
  "createdAt" : [ 2025, 4, 22, 18, 50, 19, 711705000 ],
  "lastEdited" : [ 2025, 4, 22, 18, 50, 19, 711703000 ],
  "hide" : false,
  "public" : true,
  "relatesToSkill" : [ ],
  "isCompositeOfSkill" : [ ],
  "isExtensionOfSkill" : [ ]
}