{
  "name" : "Scenario Planning for Food Supply Chain Resilience",
  "name_en" : "Scenario Planning for Food Supply Chain Resilience",
  "id" : "c4a53436-ad15-4516-93d4-1fd810d39fe5",
  "description" : "Scenario Planning for Food Supply Chain Resilience is a critical leadership skill that involves proactively identifying, analyzing, and preparing for potential disruptions within the food supply chain. In today’s volatile global environment, leaders must anticipate risks such as pandemics, geopolitical tensions, climate change, cyber-attacks, and logistical failures that can impact the availability, safety, and affordability of food. This skill requires leaders to facilitate cross-functional collaboration, gather and interpret relevant data, and construct plausible scenarios that reflect a range of possible threats and opportunities. Leaders then use these scenarios to stress-test existing supply chain strategies, identify vulnerabilities, and develop robust contingency plans. Immediate applications include conducting tabletop exercises, engaging stakeholders across the supply chain, and integrating scenario outcomes into decision-making processes to ensure business continuity and food security. The skill also encompasses the ability to communicate complex risks and mitigation strategies to diverse audiences, foster a culture of resilience, and drive continuous improvement based on lessons learned from scenario exercises. By mastering scenario planning for food supply chain resilience, leaders enable their organizations to respond swiftly and effectively to disruptions, maintain stakeholder trust, and safeguard both public health and organizational viability in the face of uncertainty.\n\nDomain: Leadership\nDomain Description: Team leadership, management, and organizational direction\nSkill Type: Personal Trait or Attitude\nSkill Areas: Organizational, Technical, Process\nRelevance Score: 1.2\nGenerated by: Frøya v2.0.0\nOperation ID: FR-20250422-d9069681",
  "description_en" : "Scenario Planning for Food Supply Chain Resilience is a critical leadership skill that involves proactively identifying, analyzing, and preparing for potential disruptions within the food supply chain. In today’s volatile global environment, leaders must anticipate risks such as pandemics, geopolitical tensions, climate change, cyber-attacks, and logistical failures that can impact the availability, safety, and affordability of food. This skill requires leaders to facilitate cross-functional collaboration, gather and interpret relevant data, and construct plausible scenarios that reflect a range of possible threats and opportunities. Leaders then use these scenarios to stress-test existing supply chain strategies, identify vulnerabilities, and develop robust contingency plans. Immediate applications include conducting tabletop exercises, engaging stakeholders across the supply chain, and integrating scenario outcomes into decision-making processes to ensure business continuity and food security. The skill also encompasses the ability to communicate complex risks and mitigation strategies to diverse audiences, foster a culture of resilience, and drive continuous improvement based on lessons learned from scenario exercises. By mastering scenario planning for food supply chain resilience, leaders enable their organizations to respond swiftly and effectively to disruptions, maintain stakeholder trust, and safeguard both public health and organizational viability in the face of uncertainty.",
  "coversElement" : {
    "classification" : "Management_Leadership"
  },
  "taggedWith" : [ ],
  "skillDomains" : [ ],
  "skillAreaCategories" : [ ],
  "matchesArea" : [ {
    "skillAreaClassification" : "Technical"
  }, {
    "skillAreaClassification" : "Organizational"
  }, {
    "skillAreaClassification" : "Process"
  } ],
  "skillType" : {
    "skillTypeClassification" : "Personal_Trait_or_Attitude"
  },
  "relatesTo" : [ ],
  "isCompositeOf" : [ ],
  "isExtensionOf" : [ ],
  "additionaljsonproperties" : null,
  "skillOwner" : "668d08a9-810e-440c-a668-531a1624694d",
  "skillOwnerUsername" : "Frøya co-worker",
  "editedBy" : "668d08a9-810e-440c-a668-531a1624694d",
  "editedByUsername" : "Frøya co-worker",
  "networkReference" : null,
  "currentVersion" : 1,
  "createdAt" : [ 2025, 4, 22, 16, 7, 14, 226411000 ],
  "lastEdited" : [ 2025, 4, 22, 16, 7, 14, 226408000 ],
  "hide" : false,
  "public" : true,
  "relatesToSkill" : [ ],
  "isCompositeOfSkill" : [ ],
  "isExtensionOfSkill" : [ ]
}