{
  "name" : "Sustainable IT Strategy Development",
  "name_en" : "Sustainable IT Strategy Development",
  "id" : "099128b7-6789-44fb-b8bd-a8456e1498ff",
  "description" : "Sustainable IT Strategy Development is a critical leadership skill focused on designing, implementing, and overseeing IT initiatives that align with organizational sustainability objectives. This skill requires leaders to integrate environmental, social, and governance (ESG) considerations into IT decision-making, ensuring that technology investments and operations contribute to long-term value creation, regulatory compliance, and positive societal impact. Practitioners must evaluate the environmental footprint of IT infrastructure, such as data centers and cloud services, and prioritize energy-efficient solutions, responsible e-waste management, and procurement of sustainable hardware. The skill also involves setting measurable sustainability targets, aligning IT roadmaps with global frameworks like the UN Sustainable Development Goals (SDGs), and ensuring compliance with regulations such as the EU Green Deal or local environmental mandates. Leaders must engage cross-functional stakeholders, foster a culture of sustainability within IT teams, and leverage digital innovation (e.g., AI for energy optimization, green software engineering) to drive continuous improvement. Typical use cases include developing green IT policies, selecting eco-friendly vendors, implementing carbon accounting tools, and reporting on IT sustainability metrics to executive leadership and external stakeholders. In today’s business environment, this skill is essential for organizations seeking to mitigate risks, enhance brand reputation, and meet the growing expectations of customers, investors, and regulators regarding sustainable business practices.\n\nDomain: Leadership\nDomain Description: Team leadership, management, and organizational direction\nSkill Type: Personal Trait or Attitude\nSkill Areas: Technical, Process, Organizational\nRelevance Score: 1.2\nGenerated by: Frøya v2.0.0\nOperation ID: FR-20250423-315125e2",
  "description_en" : "Sustainable IT Strategy Development is a critical leadership skill focused on designing, implementing, and overseeing IT initiatives that align with organizational sustainability objectives. This skill requires leaders to integrate environmental, social, and governance (ESG) considerations into IT decision-making, ensuring that technology investments and operations contribute to long-term value creation, regulatory compliance, and positive societal impact. Practitioners must evaluate the environmental footprint of IT infrastructure, such as data centers and cloud services, and prioritize energy-efficient solutions, responsible e-waste management, and procurement of sustainable hardware. The skill also involves setting measurable sustainability targets, aligning IT roadmaps with global frameworks like the UN Sustainable Development Goals (SDGs), and ensuring compliance with regulations such as the EU Green Deal or local environmental mandates. Leaders must engage cross-functional stakeholders, foster a culture of sustainability within IT teams, and leverage digital innovation (e.g., AI for energy optimization, green software engineering) to drive continuous improvement. Typical use cases include developing green IT policies, selecting eco-friendly vendors, implementing carbon accounting tools, and reporting on IT sustainability metrics to executive leadership and external stakeholders. In today’s business environment, this skill is essential for organizations seeking to mitigate risks, enhance brand reputation, and meet the growing expectations of customers, investors, and regulators regarding sustainable business practices.",
  "coversElement" : {
    "classification" : "Management_Leadership"
  },
  "taggedWith" : [ ],
  "skillDomains" : [ ],
  "skillAreaCategories" : [ ],
  "matchesArea" : [ {
    "skillAreaClassification" : "Technical"
  }, {
    "skillAreaClassification" : "Organizational"
  }, {
    "skillAreaClassification" : "Process"
  } ],
  "skillType" : {
    "skillTypeClassification" : "Personal_Trait_or_Attitude"
  },
  "relatesTo" : [ ],
  "isCompositeOf" : [ ],
  "isExtensionOf" : [ ],
  "additionaljsonproperties" : null,
  "skillOwner" : "668d08a9-810e-440c-a668-531a1624694d",
  "skillOwnerUsername" : "Frøya co-worker",
  "editedBy" : "668d08a9-810e-440c-a668-531a1624694d",
  "editedByUsername" : "Frøya co-worker",
  "networkReference" : null,
  "currentVersion" : 1,
  "createdAt" : [ 2025, 4, 23, 19, 25, 52, 13234000 ],
  "lastEdited" : [ 2025, 4, 23, 19, 25, 52, 13232000 ],
  "hide" : false,
  "public" : false,
  "relatesToSkill" : [ ],
  "isCompositeOfSkill" : [ ],
  "isExtensionOfSkill" : [ ]
}