{
  "name" : "Vector Database",
  "name_en" : null,
  "id" : "edaa4d16-14f6-4ad7-8d17-024a7c3d04c4",
  "description" : "A vector database indexes and stores vector embeddings for fast retrieval and similarity search, with capabilities like CRUD operations, metadata filtering, horizontal scaling, and serverless.\n\nWe’re in the midst of the AI revolution. It’s upending any industry it touches, promising great innovations - but it also introduces new challenges. Efficient data processing has become more crucial than ever for applications that involve large language models, generative AI, and semantic search.\n\nAll of these new applications rely on vector embeddings, a type of vector data representation that carries within it semantic information that’s critical for the AI to gain understanding and maintain a long-term memory they can draw upon when executing complex tasks. (Ref: https://www.pinecone.io/learn/vector-database/)",
  "description_en" : "Vector Database",
  "coversElement" : {
    "classification" : "Technical"
  },
  "taggedWith" : [ ],
  "matchesArea" : [ {
    "skillAreaClassification" : "Technical"
  } ],
  "skillType" : {
    "skillTypeClassification" : "Transferable_and_Functional"
  },
  "relatesTo" : [ {
    "id" : "e5af6348-2d96-4c82-a247-45c5887539d9",
    "name" : "Vector Embeddings",
    "description" : null,
    "description_en" : null
  } ],
  "isCompositeOf" : [ ],
  "isExtensionOf" : [ ],
  "additionaljsonproperties" : null,
  "skillOwner" : "61d38553-5d09-4cd3-a06a-c7173e6c1947",
  "skillOwnerUsername" : "Thor Henning Hetland",
  "editedBy" : "61d38553-5d09-4cd3-a06a-c7173e6c1947",
  "editedByUsername" : "Thor Henning Hetland",
  "networkReference" : null,
  "currentVersion" : 2,
  "createdAt" : [ 2024, 3, 13, 9, 47, 35, 278407000 ],
  "lastEdited" : [ 2024, 3, 13, 9, 50, 51, 54390000 ],
  "hide" : false,
  "public" : true,
  "relatesToSkill" : [ {
    "name" : "Vector Embeddings",
    "name_en" : null,
    "id" : "ae87ea63-0b5b-4b71-8ca5-32049a0167ef",
    "description" : "Vector Embeddings",
    "description_en" : "Vector Embeddings",
    "coversElement" : {
      "classification" : "NotSet"
    },
    "taggedWith" : [ ],
    "matchesArea" : [ ],
    "skillType" : {
      "skillTypeClassification" : "NotSet"
    },
    "relatesTo" : [ ],
    "isCompositeOf" : [ ],
    "isExtensionOf" : [ ],
    "additionaljsonproperties" : null,
    "skillOwner" : null,
    "skillOwnerUsername" : null,
    "editedBy" : null,
    "editedByUsername" : null,
    "networkReference" : null,
    "currentVersion" : 0,
    "createdAt" : null,
    "lastEdited" : null,
    "hide" : false,
    "public" : false,
    "relatesToSkill" : [ ],
    "isCompositeOfSkill" : [ ],
    "isExtensionOfSkill" : [ ]
  } ],
  "isCompositeOfSkill" : [ ],
  "isExtensionOfSkill" : [ ]
}